Metadata-Version: 1.1
Name: docketapi
Version: 0.0.4
Summary: Python client API for Docket
Home-page: https://github.com/vesche/docket-python-client
Author: Austin Jackson
Author-email: vesche@protonmail.com
License: Apache-2.0
Platform: UNKNOWN
Classifier: Development Status :: 3 - Alpha
Classifier: Intended Audience :: Information Technology
Classifier: License :: OSI Approved :: Apache Software License
Classifier: Programming Language :: Python :: 2
Classifier: Programming Language :: Python :: 2.7
Classifier: Programming Language :: Python :: 3
Classifier: Programming Language :: Python :: 3.6
Classifier: Topic :: Security
